bwo/__about__.py
bwo/__init__.py
bwo/main.py
bwo-0.1.2.dist-info/LICENSE
bwo-0.1.2.dist-info/METADATA
bwo-0.1.2.dist-info/WHEEL
bwo-0.1.2.dist-info/top_level.txt
bwo-0.1.2.dist-info/RECORD
