Metadata-Version: 2.1
Name: bwo
Version: 0.1.2
Summary: Black Widow Optimization
Home-page: https://github.com/nathanrooy/bwo
Author: Nathan A. Rooy
Author-email: nathanrooy@gmail.com
License: UNKNOWN
Platform: UNKNOWN
Classifier: Programming Language :: Python :: 3
Classifier: License :: OSI Approved :: MIT License
Classifier: Operating System :: OS Independent
Requires-Python: >=3.5
